abc_delegation/__init__.py
abc_delegation/delegate.py
abc_delegation/multi_delegate.py
abc_delegation-0.3.1.dist-info/LICENSE
abc_delegation-0.3.1.dist-info/WHEEL
abc_delegation-0.3.1.dist-info/METADATA
abc_delegation-0.3.1.dist-info/RECORD
