Metadata-Version: 2.1
Name: abc-delegation
Version: 0.3.1
Summary: A tool for automated delegation with abstract base classes
Home-page: https://github.com/monomonedula/abc-delegation
License: MIT
Keywords: decorator,delegation,ABC,abstract-base-class,metaclasses,utility
Author: Vladyslav Halchenko
Author-email: valh@tuta.io
Requires-Python: >=3.6,<4.0
Classifier: License :: OSI Approved :: MIT License
Classifier: Programming Language :: Python :: 3
Classifier: Programming Language :: Python :: 3.6
Classifier: Programming Language :: Python :: 3.7
Classifier: Programming Language :: Python :: 3.8
Project-URL: Repository, https://github.com/monomonedula/abc-delegation
